multiplexer/__init__.py
multiplexer/client.py
multiplexer/multiplexer.py
multiplexer-0.0.7.dist-info/METADATA
multiplexer-0.0.7.dist-info/WHEEL
multiplexer-0.0.7.dist-info/top_level.txt
multiplexer-0.0.7.dist-info/RECORD
